{
  "voc_eval_res": {
    "precision": 52.5296,
    "recall": 30.8665,
    "f-score": 38.8845
  },
  "KL_res": {
    "KL divergence": 1.0016276604053638,
    "Euclidean Dist.": 0.06357157225572307,
    "WER": 0.6517943743937924,
    "CER": 0.37037881378471826,
    "Cosine Dist.": 0.09161026064358568
  },
  "occ_eval_res": {
    "precision": 56.2144,
    "recall": 54.2515,
    "f-score": 55.2155
  },
  "clean_eval": {
    "f-score": 31.295925183700735,
    "precision": 31.2021312021312,
    "recall": 31.39028475711893,
    "tp": 937,
    "fp": 2066,
    "fn": 2048
  },
  "jaccard": [
    0.424690857490371
  ],
  "braycurtis": [
    0.13499903901595234
  ],
  "dice": [
    0.2695920730922661
  ],
  "cosinus": [
    0.019166001994761594
  ]
}