{
  "voc_eval_res": {
    "precision": 70.4663,
    "recall": 39.1931,
    "f-score": 50.3704
  },
  "KL_res": {
    "KL divergence": 1.0318804665493384,
    "Euclidean Dist.": 0.25368753230695207,
    "WER": 0.6539833531510107,
    "CER": 0.44409756097560976,
    "Cosine Dist.": 0.05051995391146846
  },
  "occ_eval_res": {
    "precision": 58.2393,
    "recall": 61.3555,
    "f-score": 59.7568
  },
  "clean_eval": {
    "f-score": 21.71628721541156,
    "precision": 22.382671480144403,
    "recall": 21.08843537414966,
    "tp": 186,
    "fp": 645,
    "fn": 696
  },
  "jaccard": [
    0.45514950166112955
  ],
  "braycurtis": [
    0.250961168781238
  ],
  "dice": [
    0.2946236559139785
  ],
  "cosinus": [
    0.10060577287242001
  ]
}