{
  "voc_eval_res": {
    "precision": 79.3651,
    "recall": 55.5556,
    "f-score": 65.3595
  },
  "KL_res": {
    "KL divergence": 0.9959864308379485,
    "Euclidean Dist.": 0.05992103128257441,
    "WER": 0.4467821782178218,
    "CER": 0.3456108041743401,
    "Cosine Dist.": 0.054892369542438924
  },
  "occ_eval_res": {
    "precision": 83.0065,
    "recall": 62.8713,
    "f-score": 71.5493
  },
  "clean_eval": {
    "f-score": 62.999999999999986,
    "precision": 55.541561712846345,
    "recall": 72.77227722772277,
    "tp": 441,
    "fp": 353,
    "fn": 165
  },
  "jaccard": [
    0.3135593220338983
  ],
  "braycurtis": [
    0.1437296076298837
  ],
  "dice": [
    0.18592964824120603
  ],
  "cosinus": [
    0.01740796179954618
  ]
}