{
  "entite_0": {
    "label": "LOC",
    "text": "Genevieve de Brabant",
    "jalons": [
      236,
      256
    ]
  },
  "entite_1": {
    "label": "MISC",
    "text": "monter dans la carriole du pere Chicon",
    "jalons": [
      18,
      56
    ]
  },
  "entite_2": {
    "label": "LOC",
    "text": "Paris",
    "jalons": [
      366,
      371
    ]
  },
  "entite_3": {
    "label": "LOC",
    "text": "France",
    "jalons": [
      58,
      64
    ]
  },
  "entite_4": {
    "label": "LOC",
    "text": "Ismerie",
    "jalons": [
      488,
      495
    ]
  },
  "entite_5": {
    "label": "LOC",
    "text": "Marie-Aime",
    "jalons": [
      137,
      147
    ]
  },
  "entite_6": {
    "label": "LOC",
    "text": "Marie-Aime",
    "jalons": [
      96,
      106
    ]
  },
  "entite_7": {
    "label": "PER",
    "text": "Ma Sœur",
    "jalons": [
      147,
      154
    ]
  },
  "entite_8": {
    "label": "LOC",
    "text": "Autour de moi",
    "jalons": [
      498,
      511
    ]
  },
  "entite_9": {
    "label": "PER",
    "text": "Marie Renaud",
    "jalons": [
      455,
      467
    ]
  },
  "entite_10": {
    "label": "LOC",
    "text": "Gabrielle",
    "jalons": [
      446,
      455
    ]
  },
  "entite_11": {
    "label": "PER",
    "text": "le n'aimait pas cette sur Aimee",
    "jalons": [
      0,
      31
    ]
  },
  "entite_12": {
    "label": "LOC",
    "text": "Gabrielle",
    "jalons": [
      278,
      287
    ]
  },
  "entite_13": {
    "label": "LOC",
    "text": "Marie",
    "jalons": [
      70,
      75
    ]
  },
  "entite_14": {
    "label": "LOC",
    "text": "Marie",
    "jalons": [
      81,
      86
    ]
  },
  "entite_15": {
    "label": "LOC",
    "text": "Aime",
    "jalons": [
      88,
      92
    ]
  },
  "entite_16": {
    "label": "PER",
    "text": "Bonne Esther",
    "jalons": [
      111,
      123
    ]
  },
  "entite_17": {
    "label": "PER",
    "text": "Bonne Neron",
    "jalons": [
      296,
      307
    ]
  },
  "entite_18": {
    "label": "PER",
    "text": "Bonne Esther",
    "jalons": [
      125,
      137
    ]
  },
  "entite_19": {
    "label": "PER",
    "text": "Bonne Esther",
    "jalons": [
      157,
      169
    ]
  },
  "entite_20": {
    "label": "PER",
    "text": "Bonne Esther",
    "jalons": [
      30,
      42
    ]
  },
  "entite_21": {
    "label": "PER",
    "text": "Bonne Esther",
    "jalons": [
      475,
      487
    ]
  },
  "entite_22": {
    "label": "PER",
    "text": "Marie Renaud",
    "jalons": [
      119,
      131
    ]
  },
  "entite_23": {
    "label": "MISC",
    "text": "Elle me prit dans ses bras Elle me passait la man sur le",
    "jalons": [
      8,
      64
    ]
  },
  "entite_24": {
    "label": "MISC",
    "text": "Ismerie qui parle",
    "jalons": [
      206,
      223
    ]
  },
  "entite_25": {
    "label": "MISC",
    "text": "Voila encore sur Marie-Aimee qui gronde",
    "jalons": [
      246,
      285
    ]
  },
  "entite_26": {
    "label": "MISC",
    "text": "Dans la suite",
    "jalons": [
      385,
      398
    ]
  },
  "entite_27": {
    "label": "LOC",
    "text": "Marie",
    "jalons": [
      172,
      177
    ]
  },
  "entite_28": {
    "label": "LOC",
    "text": "Aime",
    "jalons": [
      179,
      183
    ]
  },
  "entite_29": {
    "label": "PER",
    "text": "Marie Renaud",
    "jalons": [
      320,
      332
    ]
  },
  "entite_30": {
    "label": "PER",
    "text": "Marie Renaud",
    "jalons": [
      446,
      458
    ]
  },
  "entite_31": {
    "label": "PER",
    "text": "Marie Renaud",
    "jalons": [
      237,
      249
    ]
  },
  "entite_32": {
    "label": "PER",
    "text": "Bonne Neron",
    "jalons": [
      286,
      297
    ]
  },
  "entite_33": {
    "label": "PER",
    "text": "Bonne Neron",
    "jalons": [
      368,
      379
    ]
  },
  "entite_34": {
    "label": "PER",
    "text": "que Bonne Neron",
    "jalons": [
      54,
      69
    ]
  },
  "entite_35": {
    "label": "MISC",
    "text": "soeur Marie-Aimee me chargea de les lui",
    "jalons": [
      0,
      39
    ]
  },
  "entite_36": {
    "label": "PER",
    "text": "Marie Renaud",
    "jalons": [
      51,
      63
    ]
  },
  "entite_37": {
    "label": "LOC",
    "text": "Marie",
    "jalons": [
      71,
      76
    ]
  },
  "entite_38": {
    "label": "PER",
    "text": "Bonne Neron",
    "jalons": [
      473,
      484
    ]
  },
  "entite_39": {
    "label": "PER",
    "text": "Madeleine",
    "jalons": [
      91,
      100
    ]
  },
  "entite_40": {
    "label": "PER",
    "text": "Marie Renaud",
    "jalons": [
      292,
      304
    ]
  },
  "entite_41": {
    "label": "PER",
    "text": "Elle lui",
    "jalons": [
      306,
      314
    ]
  },
  "entite_42": {
    "label": "PER",
    "text": "Marie Renaud",
    "jalons": [
      344,
      356
    ]
  },
  "entite_43": {
    "label": "PER",
    "text": "Madeleine",
    "jalons": [
      458,
      467
    ]
  },
  "entite_44": {
    "label": "PER",
    "text": "Seur Marie",
    "jalons": [
      380,
      390
    ]
  },
  "entite_45": {
    "label": "PER",
    "text": "Aimee me",
    "jalons": [
      392,
      400
    ]
  },
  "entite_46": {
    "label": "PER",
    "text": "Elle m'envoya",
    "jalons": [
      4,
      17
    ]
  },
  "entite_47": {
    "label": "LOC",
    "text": "Sur Ma",
    "jalons": [
      506,
      512
    ]
  },
  "entite_48": {
    "label": "MISC",
    "text": "Seur Marie-Aimee les arreta d'un",
    "jalons": [
      264,
      296
    ]
  },
  "entite_49": {
    "label": "PER",
    "text": "Malgre moi",
    "jalons": [
      29,
      39
    ]
  },
  "entite_50": {
    "label": "PER",
    "text": "Marie-Aime Pas-dessus de",
    "jalons": [
      18,
      42
    ]
  },
  "entite_51": {
    "label": "PER",
    "text": "Je la revoyais",
    "jalons": [
      61,
      75
    ]
  },
  "entite_52": {
    "label": "LOC",
    "text": "Elle ouvrait la porte",
    "jalons": [
      461,
      482
    ]
  },
  "entite_53": {
    "label": "LOC",
    "text": "la porte de la",
    "jalons": [
      391,
      405
    ]
  },
  "entite_54": {
    "label": "LOC",
    "text": "la porte de la salle",
    "jalons": [
      483,
      503
    ]
  },
  "entite_55": {
    "label": "LOC",
    "text": "Elle",
    "jalons": [
      505,
      509
    ]
  },
  "entite_56": {
    "label": "LOC",
    "text": "pensais",
    "jalons": [
      1,
      8
    ]
  },
  "entite_57": {
    "label": "MISC",
    "text": "MARIE-CLAIRE Le moment de la premiere",
    "jalons": [
      55,
      92
    ]
  },
  "entite_58": {
    "label": "PER",
    "text": "Sophie",
    "jalons": [
      76,
      82
    ]
  },
  "entite_59": {
    "label": "PER",
    "text": "Elle n'etait",
    "jalons": [
      84,
      96
    ]
  },
  "entite_60": {
    "label": "PER",
    "text": "Elle m'avoua",
    "jalons": [
      471,
      483
    ]
  },
  "entite_61": {
    "label": "LOC",
    "text": "Marie-Aime",
    "jalons": [
      91,
      101
    ]
  },
  "entite_62": {
    "label": "PER",
    "text": "Je n'etai",
    "jalons": [
      503,
      512
    ]
  },
  "entite_63": {
    "label": "MISC",
    "text": "Bonne Justine nous",
    "jalons": [
      101,
      119
    ]
  },
  "entite_64": {
    "label": "PER",
    "text": "Marie Renaud",
    "jalons": [
      201,
      213
    ]
  },
  "entite_65": {
    "label": "PER",
    "text": "sait chanter Colette",
    "jalons": [
      0,
      20
    ]
  },
  "entite_66": {
    "label": "PER",
    "text": "Bonne Justine",
    "jalons": [
      234,
      247
    ]
  },
  "entite_67": {
    "label": "PER",
    "text": "Bonne Justine",
    "jalons": [
      213,
      226
    ]
  },
  "entite_68": {
    "label": "LOC",
    "text": "MARIE-CLAIRB",
    "jalons": [
      421,
      433
    ]
  },
  "entite_69": {
    "label": "LOC",
    "text": "Merci",
    "jalons": [
      436,
      441
    ]
  },
  "entite_70": {
    "label": "LOC",
    "text": "Marie-Claire",
    "jalons": [
      443,
      455
    ]
  },
  "entite_71": {
    "label": "PER",
    "text": "Colette",
    "jalons": [
      475,
      482
    ]
  },
  "entite_72": {
    "label": "PER",
    "text": "Bonne Justine",
    "jalons": [
      484,
      497
    ]
  },
  "entite_73": {
    "label": "PER",
    "text": "Madeleine",
    "jalons": [
      70,
      79
    ]
  },
  "entite_74": {
    "label": "LOC",
    "text": "Va",
    "jalons": [
      99,
      101
    ]
  },
  "entite_75": {
    "label": "LOC",
    "text": "Ismerie",
    "jalons": [
      415,
      422
    ]
  },
  "entite_76": {
    "label": "LOC",
    "text": "Si",
    "jalons": [
      425,
      427
    ]
  },
  "entite_77": {
    "label": "PER",
    "text": "Elle me repoussa",
    "jalons": [
      489,
      505
    ]
  },
  "entite_78": {
    "label": "LOC",
    "text": "Ohl",
    "jalons": [
      509,
      512
    ]
  },
  "entite_79": {
    "label": "PER",
    "text": "Elle me",
    "jalons": [
      85,
      92
    ]
  },
  "entite_80": {
    "label": "LOC",
    "text": "Aussitôt",
    "jalons": [
      340,
      348
    ]
  },
  "entite_81": {
    "label": "LOC",
    "text": "de la Vierge",
    "jalons": [
      351,
      363
    ]
  },
  "entite_82": {
    "label": "PER",
    "text": "Miroir de Justice",
    "jalons": [
      336,
      353
    ]
  },
  "entite_83": {
    "label": "PER",
    "text": "Miroir de Justice",
    "jalons": [
      458,
      475
    ]
  },
  "entite_84": {
    "label": "PER",
    "text": "guerissez ColettelMaintenant",
    "jalons": [
      477,
      505
    ]
  },
  "entite_85": {
    "label": "PER",
    "text": "Colet",
    "jalons": [
      507,
      512
    ]
  },
  "entite_86": {
    "label": "LOC",
    "text": "Aussitot",
    "jalons": [
      219,
      227
    ]
  },
  "entite_87": {
    "label": "LOC",
    "text": "de la Vierge",
    "jalons": [
      423,
      435
    ]
  },
  "entite_88": {
    "label": "PER",
    "text": "de Colette",
    "jalons": [
      501,
      511
    ]
  },
  "entite_89": {
    "label": "MISC",
    "text": "Elle s'avisa un dimanche de me faire",
    "jalons": [
      248,
      284
    ]
  },
  "entite_90": {
    "label": "LOC",
    "text": "Madeleine",
    "jalons": [
      113,
      122
    ]
  },
  "entite_91": {
    "label": "MISC",
    "text": "La voix de Colette monta",
    "jalons": [
      221,
      245
    ]
  },
  "entite_92": {
    "label": "LOC",
    "text": "Marie-Aime",
    "jalons": [
      35,
      45
    ]
  },
  "entite_93": {
    "label": "PER",
    "text": "Madeleine",
    "jalons": [
      1,
      10
    ]
  },
  "entite_94": {
    "label": "PER",
    "text": "Marie Renaud",
    "jalons": [
      32,
      44
    ]
  },
  "entite_95": {
    "label": "PER",
    "text": "Aussitot Marie Renaud avait",
    "jalons": [
      46,
      73
    ]
  },
  "entite_96": {
    "label": "MISC",
    "text": "dans la chambre de sur Marie- Aimee et Madeleine avait",
    "jalons": [
      209,
      263
    ]
  },
  "entite_97": {
    "label": "PER",
    "text": "Madeleine",
    "jalons": [
      366,
      375
    ]
  },
  "entite_98": {
    "label": "LOC",
    "text": "Rome",
    "jalons": [
      177,
      181
    ]
  },
  "entite_99": {
    "label": "PER",
    "text": "Mlle Maximilienne",
    "jalons": [
      114,
      131
    ]
  },
  "entite_100": {
    "label": "LOC",
    "text": "de la Sologne",
    "jalons": [
      206,
      219
    ]
  },
  "entite_101": {
    "label": "LOC",
    "text": "Bien",
    "jalons": [
      385,
      389
    ]
  },
  "entite_102": {
    "label": "LOC",
    "text": "Bien",
    "jalons": [
      424,
      428
    ]
  },
  "entite_103": {
    "label": "MISC",
    "text": "Elle se haussa sur les bras de",
    "jalons": [
      439,
      469
    ]
  },
  "entite_104": {
    "label": "LOC",
    "text": "la veille du jour de la Saint-eau",
    "jalons": [
      81,
      114
    ]
  },
  "entite_105": {
    "label": "LOC",
    "text": "Marie-Aime",
    "jalons": [
      497,
      507
    ]
  },
  "entite_106": {
    "label": "PER",
    "text": "Marie Renaud",
    "jalons": [
      52,
      64
    ]
  },
  "entite_107": {
    "label": "MISC",
    "text": "J'avais un peu honte de moi",
    "jalons": [
      65,
      92
    ]
  },
  "entite_108": {
    "label": "LOC",
    "text": "Saint-Jean",
    "jalons": [
      165,
      175
    ]
  },
  "entite_109": {
    "label": "LOC",
    "text": "Ismerie",
    "jalons": [
      33,
      40
    ]
  },
  "entite_110": {
    "label": "MISC",
    "text": "sa sur jumelle Chemineau la Bete",
    "jalons": [
      0,
      32
    ]
  },
  "entite_111": {
    "label": "MISC",
    "text": "Chemineau la Bete etait de",
    "jalons": [
      330,
      356
    ]
  },
  "entite_112": {
    "label": "PER",
    "text": "chien de garde de sa",
    "jalons": [
      1,
      21
    ]
  },
  "entite_113": {
    "label": "MISC",
    "text": "vraie croix ou a un morceau du voile de la Vierge",
    "jalons": [
      0,
      49
    ]
  },
  "entite_114": {
    "label": "LOC",
    "text": "Bien",
    "jalons": [
      210,
      214
    ]
  },
  "entite_115": {
    "label": "MISC",
    "text": "Seur Marie-Aimee la renvoya en",
    "jalons": [
      64,
      94
    ]
  },
  "entite_116": {
    "label": "MISC",
    "text": "Jure-moi que tu diras tous les soirs un De Profundis pour lui",
    "jalons": [
      368,
      429
    ]
  },
  "entite_117": {
    "label": "LOC",
    "text": "Pauline",
    "jalons": [
      417,
      424
    ]
  },
  "entite_118": {
    "label": "LOC",
    "text": "Jappe",
    "jalons": [
      52,
      57
    ]
  },
  "entite_119": {
    "label": "LOC",
    "text": "Castle,Appela",
    "jalons": [
      59,
      72
    ]
  },
  "entite_120": {
    "label": "PER",
    "text": "Maitre Sylvain",
    "jalons": [
      484,
      498
    ]
  },
  "entite_121": {
    "label": "PER",
    "text": "J'avais une si grande envie de la voir",
    "jalons": [
      192,
      230
    ]
  },
  "entite_122": {
    "label": "PER",
    "text": "j'eus l'idee de lui",
    "jalons": [
      493,
      512
    ]
  },
  "entite_123": {
    "label": "PER",
    "text": "J'en restai",
    "jalons": [
      7,
      18
    ]
  },
  "entite_124": {
    "label": "PER",
    "text": "Le Mati",
    "jalons": [
      505,
      512
    ]
  },
  "entite_125": {
    "label": "LOC",
    "text": "Celle de",
    "jalons": [
      450,
      458
    ]
  },
  "entite_126": {
    "label": "MISC",
    "text": "ui avait un bonnet de coton",
    "jalons": [
      0,
      27
    ]
  },
  "entite_127": {
    "label": "PER",
    "text": "J'tais si lasse que je",
    "jalons": [
      3,
      25
    ]
  },
  "entite_128": {
    "label": "LOC",
    "text": "Marie-Aime",
    "jalons": [
      401,
      411
    ]
  },
  "entite_129": {
    "label": "PER",
    "text": "Marie",
    "jalons": [
      507,
      512
    ]
  },
  "entite_130": {
    "label": "LOC",
    "text": "Marie-Aime",
    "jalons": [
      374,
      384
    ]
  },
  "entite_131": {
    "label": "LOC",
    "text": "Allons",
    "jalons": [
      200,
      206
    ]
  },
  "entite_132": {
    "label": "LOC",
    "text": "Marie-Aime",
    "jalons": [
      90,
      100
    ]
  },
  "entite_133": {
    "label": "PER",
    "text": "Moi",
    "jalons": [
      507,
      510
    ]
  },
  "entite_134": {
    "label": "LOC",
    "text": "ARrêter",
    "jalons": [
      247,
      254
    ]
  },
  "entite_135": {
    "label": "LOC",
    "text": "laine",
    "jalons": [
      504,
      509
    ]
  },
  "entite_136": {
    "label": "LOC",
    "text": "Eugkne",
    "jalons": [
      423,
      429
    ]
  },
  "entite_137": {
    "label": "LOC",
    "text": "de la Sologne",
    "jalons": [
      260,
      273
    ]
  },
  "entite_138": {
    "label": "PER",
    "text": "Martine",
    "jalons": [
      483,
      490
    ]
  },
  "entite_139": {
    "label": "PER",
    "text": "ieu du troupeau",
    "jalons": [
      0,
      15
    ]
  },
  "entite_140": {
    "label": "PER",
    "text": "Castille",
    "jalons": [
      504,
      512
    ]
  },
  "entite_141": {
    "label": "LOC",
    "text": "Castille",
    "jalons": [
      63,
      71
    ]
  },
  "entite_142": {
    "label": "MISC",
    "text": "MARIE-CLAIRE Tout le monde sortit de la maison en",
    "jalons": [
      307,
      356
    ]
  },
  "entite_143": {
    "label": "MISC",
    "text": "ser chaque jiour pres d'un bois de jeunes  ainsi",
    "jalons": [
      0,
      48
    ]
  },
  "entite_144": {
    "label": "LOC",
    "text": "Madeleine",
    "jalons": [
      73,
      82
    ]
  },
  "entite_145": {
    "label": "MISC",
    "text": "Elle avait comme elle les yeux tres eloignes l'un de l'autre",
    "jalons": [
      84,
      144
    ]
  },
  "entite_146": {
    "label": "LOC",
    "text": "Sainte-Montagne",
    "jalons": [
      465,
      480
    ]
  },
  "entite_147": {
    "label": "PER",
    "text": "Martine m'entratna",
    "jalons": [
      35,
      53
    ]
  },
  "entite_148": {
    "label": "MISC",
    "text": "uberge du Cheval Blanc",
    "jalons": [
      0,
      22
    ]
  },
  "entite_149": {
    "label": "MISC",
    "text": "Il en sortait un grand bruit de voix et de",
    "jalons": [
      24,
      66
    ]
  },
  "entite_150": {
    "label": "LOC",
    "text": "Eugene",
    "jalons": [
      261,
      267
    ]
  },
  "entite_151": {
    "label": "LOC",
    "text": "Sainte-Montagne",
    "jalons": [
      100,
      115
    ]
  },
  "entite_152": {
    "label": "LOC",
    "text": "Eugene",
    "jalons": [
      451,
      457
    ]
  },
  "entite_153": {
    "label": "PER",
    "text": "Pauline me dit de",
    "jalons": [
      248,
      265
    ]
  },
  "entite_154": {
    "label": "PER",
    "text": "Pauline me",
    "jalons": [
      463,
      473
    ]
  },
  "entite_155": {
    "label": "LOC",
    "text": "Telemaque",
    "jalons": [
      367,
      376
    ]
  },
  "entite_156": {
    "label": "PER",
    "text": "Pauline me",
    "jalons": [
      81,
      91
    ]
  },
  "entite_157": {
    "label": "PER",
    "text": "Mattre Sylvain",
    "jalons": [
      58,
      72
    ]
  },
  "entite_158": {
    "label": "PER",
    "text": "Pauline lui",
    "jalons": [
      123,
      134
    ]
  },
  "entite_159": {
    "label": "LOC",
    "text": "La",
    "jalons": [
      507,
      509
    ]
  },
  "entite_160": {
    "label": "PER",
    "text": "Pauline repondait",
    "jalons": [
      5,
      22
    ]
  },
  "entite_161": {
    "label": "PER",
    "text": "Pauline",
    "jalons": [
      15,
      22
    ]
  },
  "entite_162": {
    "label": "PER",
    "text": "M. Tirande",
    "jalons": [
      449,
      459
    ]
  },
  "entite_163": {
    "label": "PER",
    "text": "M. Tirande",
    "jalons": [
      395,
      405
    ]
  },
  "entite_164": {
    "label": "LOC",
    "text": "Tirande",
    "jalons": [
      353,
      360
    ]
  },
  "entite_165": {
    "label": "LOC",
    "text": "Tirande",
    "jalons": [
      124,
      131
    ]
  },
  "entite_166": {
    "label": "LOC",
    "text": "Eugene",
    "jalons": [
      133,
      139
    ]
  },
  "entite_167": {
    "label": "MISC",
    "text": "uline combien le fermier avait eu pitie de moi en me voyant",
    "jalons": [
      0,
      59
    ]
  },
  "entite_168": {
    "label": "MISC",
    "text": "Bonne Justine",
    "jalons": [
      67,
      80
    ]
  },
  "entite_169": {
    "label": "LOC",
    "text": "Le clair de",
    "jalons": [
      174,
      185
    ]
  },
  "entite_170": {
    "label": "MISC",
    "text": "gne de croix vers la maison, elle ramassa les",
    "jalons": [
      0,
      45
    ]
  },
  "entite_171": {
    "label": "PER",
    "text": "Elle ajouta",
    "jalons": [
      47,
      58
    ]
  },
  "entite_172": {
    "label": "PER",
    "text": "M. et Mme Alphonse",
    "jalons": [
      348,
      366
    ]
  },
  "entite_173": {
    "label": "MISC",
    "text": "Des la premiere semaine",
    "jalons": [
      368,
      391
    ]
  },
  "entite_174": {
    "label": "LOC",
    "text": "Tirande",
    "jalons": [
      294,
      301
    ]
  },
  "entite_175": {
    "label": "PER",
    "text": "Pauline ou Eugne",
    "jalons": [
      443,
      459
    ]
  },
  "entite_176": {
    "label": "PER",
    "text": "Jean le Rouge",
    "jalons": [
      95,
      108
    ]
  },
  "entite_177": {
    "label": "PER",
    "text": "Jean le Rouge",
    "jalons": [
      330,
      343
    ]
  },
  "entite_178": {
    "label": "LOC",
    "text": "Villevieille",
    "jalons": [
      399,
      411
    ]
  },
  "entite_179": {
    "label": "LOC",
    "text": "Sylvain",
    "jalons": [
      453,
      460
    ]
  },
  "entite_180": {
    "label": "PER",
    "text": "Eugene disait",
    "jalons": [
      494,
      507
    ]
  },
  "entite_181": {
    "label": "PER",
    "text": "M. Alphonse",
    "jalons": [
      105,
      116
    ]
  },
  "entite_182": {
    "label": "PER",
    "text": "Jean le Rouge",
    "jalons": [
      200,
      213
    ]
  },
  "entite_183": {
    "label": "PER",
    "text": "Jean le Rouge",
    "jalons": [
      464,
      477
    ]
  },
  "entite_184": {
    "label": "MISC",
    "text": "Puis le malheur arriva, un soir de Noel",
    "jalons": [
      9,
      48
    ]
  },
  "entite_185": {
    "label": "PER",
    "text": "Jean le Rouge",
    "jalons": [
      414,
      427
    ]
  },
  "entite_186": {
    "label": "ORG",
    "text": "La Femme",
    "jalons": [
      490,
      498
    ]
  },
  "entite_187": {
    "label": "PER",
    "text": "M. Alphonse",
    "jalons": [
      500,
      511
    ]
  },
  "entite_188": {
    "label": "PER",
    "text": "Jean le Rouge",
    "jalons": [
      413,
      426
    ]
  },
  "entite_189": {
    "label": "LOC",
    "text": "Villevieille",
    "jalons": [
      418,
      430
    ]
  },
  "entite_190": {
    "label": "LOC",
    "text": "Aussitot",
    "jalons": [
      492,
      500
    ]
  },
  "entite_191": {
    "label": "PER",
    "text": "Jean le Rouge",
    "jalons": [
      3,
      16
    ]
  },
  "entite_192": {
    "label": "MISC",
    "text": "quitta la maison de la colline a la fin de janvier",
    "jalons": [
      17,
      67
    ]
  },
  "entite_193": {
    "label": "PER",
    "text": "M. Alphonse",
    "jalons": [
      280,
      291
    ]
  },
  "entite_194": {
    "label": "PER",
    "text": "ur moi",
    "jalons": [
      0,
      6
    ]
  },
  "entite_195": {
    "label": "LOC",
    "text": "Villevieille",
    "jalons": [
      197,
      209
    ]
  },
  "entite_196": {
    "label": "LOC",
    "text": "le pas de la porte",
    "jalons": [
      0,
      18
    ]
  },
  "entite_197": {
    "label": "LOC",
    "text": "Villevieille",
    "jalons": [
      395,
      407
    ]
  },
  "entite_198": {
    "label": "LOC",
    "text": "Pauline",
    "jalons": [
      462,
      469
    ]
  },
  "entite_199": {
    "label": "LOC",
    "text": "Alphonse",
    "jalons": [
      128,
      136
    ]
  },
  "entite_200": {
    "label": "LOC",
    "text": "Narie-Aime",
    "jalons": [
      470,
      480
    ]
  },
  "entite_201": {
    "label": "PER",
    "text": "Jusqu'a Jean le Rouge",
    "jalons": [
      359,
      380
    ]
  },
  "entite_202": {
    "label": "LOC",
    "text": "Gue",
    "jalons": [
      337,
      340
    ]
  },
  "entite_203": {
    "label": "LOC",
    "text": "Perdu",
    "jalons": [
      342,
      347
    ]
  },
  "entite_204": {
    "label": "LOC",
    "text": "Paris",
    "jalons": [
      178,
      183
    ]
  },
  "entite_205": {
    "label": "LOC",
    "text": "Tiens",
    "jalons": [
      280,
      285
    ]
  },
  "entite_206": {
    "label": "LOC",
    "text": "Henri",
    "jalons": [
      293,
      298
    ]
  },
  "entite_207": {
    "label": "PER",
    "text": "Mme Alphonse lui",
    "jalons": [
      483,
      499
    ]
  },
  "entite_208": {
    "label": "LOC",
    "text": "Si",
    "jalons": [
      507,
      509
    ]
  },
  "entite_209": {
    "label": "PER",
    "text": "Henri Deslois",
    "jalons": [
      5,
      18
    ]
  },
  "entite_210": {
    "label": "LOC",
    "text": "Villevieille",
    "jalons": [
      373,
      385
    ]
  },
  "entite_211": {
    "label": "LOC",
    "text": "Illll",
    "jalons": [
      0,
      5
    ]
  },
  "entite_212": {
    "label": "PER",
    "text": "Jean le Rouge",
    "jalons": [
      52,
      65
    ]
  },
  "entite_213": {
    "label": "LOC",
    "text": "L'ecorc",
    "jalons": [
      505,
      512
    ]
  },
  "entite_214": {
    "label": "LOC",
    "text": "Voici la",
    "jalons": [
      353,
      361
    ]
  },
  "entite_215": {
    "label": "PER",
    "text": "Henri Deslois",
    "jalons": [
      189,
      202
    ]
  },
  "entite_216": {
    "label": "LOC",
    "text": "Hier",
    "jalons": [
      380,
      384
    ]
  },
  "entite_217": {
    "label": "PER",
    "text": "Henri Deslois",
    "jalons": [
      386,
      399
    ]
  },
  "entite_218": {
    "label": "MISC",
    "text": "au jardin de la terre",
    "jalons": [
      0,
      21
    ]
  },
  "entite_219": {
    "label": "LOC",
    "text": "le seuil de la ferme de Ville",
    "jalons": [
      396,
      425
    ]
  },
  "entite_220": {
    "label": "PER",
    "text": "Henri Deslois",
    "jalons": [
      489,
      502
    ]
  },
  "entite_221": {
    "label": "MISC",
    "text": "la cloche de l'eglise de Sainte-Montagne se mit a sonner",
    "jalons": [
      25,
      81
    ]
  },
  "entite_222": {
    "label": "PER",
    "text": "Henri Deslois",
    "jalons": [
      465,
      478
    ]
  },
  "entite_223": {
    "label": "MISC",
    "text": "me ramena sur le chemin de la fer",
    "jalons": [
      479,
      512
    ]
  },
  "entite_224": {
    "label": "LOC",
    "text": "Marie-Aime",
    "jalons": [
      153,
      163
    ]
  },
  "entite_225": {
    "label": "LOC",
    "text": "La maison de la",
    "jalons": [
      165,
      180
    ]
  },
  "entite_226": {
    "label": "PER",
    "text": "Henri Deslois",
    "jalons": [
      241,
      254
    ]
  },
  "entite_227": {
    "label": "PER",
    "text": "Henri",
    "jalons": [
      506,
      511
    ]
  },
  "entite_228": {
    "label": "PER",
    "text": "Henri Deslois",
    "jalons": [
      144,
      157
    ]
  },
  "entite_229": {
    "label": "LOC",
    "text": "Marie-Aime",
    "jalons": [
      221,
      231
    ]
  },
  "entite_230": {
    "label": "PER",
    "text": "Henri Deslois",
    "jalons": [
      260,
      273
    ]
  },
  "entite_231": {
    "label": "PER",
    "text": "Henri Deslois",
    "jalons": [
      57,
      70
    ]
  },
  "entite_232": {
    "label": "PER",
    "text": "Henri Deslois",
    "jalons": [
      428,
      441
    ]
  },
  "entite_233": {
    "label": "MISC",
    "text": "dans la piece qui donnait sur le jardin",
    "jalons": [
      1,
      40
    ]
  },
  "entite_234": {
    "label": "PER",
    "text": "Henri Deslois",
    "jalons": [
      218,
      231
    ]
  },
  "entite_235": {
    "label": "LOC",
    "text": "Villevieille",
    "jalons": [
      241,
      253
    ]
  },
  "entite_236": {
    "label": "PER",
    "text": "Mme Alphonse",
    "jalons": [
      30,
      42
    ]
  },
  "entite_237": {
    "label": "LOC",
    "text": "Aussitot",
    "jalons": [
      44,
      52
    ]
  },
  "entite_238": {
    "label": "LOC",
    "text": "Alphonse",
    "jalons": [
      371,
      379
    ]
  },
  "entite_239": {
    "label": "PER",
    "text": "M. Alphonse lui",
    "jalons": [
      489,
      504
    ]
  },
  "entite_240": {
    "label": "MISC",
    "text": "Vous savez que j'ai vendu la maison de la",
    "jalons": [
      1,
      42
    ]
  },
  "entite_241": {
    "label": "PER",
    "text": "Henri Deslois",
    "jalons": [
      498,
      511
    ]
  },
  "entite_242": {
    "label": "PER",
    "text": "vint s'asseoir",
    "jalons": [
      0,
      14
    ]
  },
  "entite_243": {
    "label": "LOC",
    "text": "Blanchet",
    "jalons": [
      320,
      328
    ]
  },
  "entite_244": {
    "label": "PER",
    "text": "Jean le Rouge",
    "jalons": [
      471,
      484
    ]
  },
  "entite_245": {
    "label": "PER",
    "text": "M. Alphonse",
    "jalons": [
      486,
      497
    ]
  },
  "entite_246": {
    "label": "PER",
    "text": "Henri Deslois",
    "jalons": [
      91,
      104
    ]
  },
  "entite_247": {
    "label": "PER",
    "text": "Mais M. Alphonse la",
    "jalons": [
      467,
      486
    ]
  },
  "entite_248": {
    "label": "LOC",
    "text": "Sainte-Montagne",
    "jalons": [
      191,
      206
    ]
  },
  "entite_249": {
    "label": "LOC",
    "text": "Aussitot",
    "jalons": [
      268,
      276
    ]
  },
  "entite_250": {
    "label": "PER",
    "text": "M. Alphonse",
    "jalons": [
      152,
      163
    ]
  },
  "entite_251": {
    "label": "MISC",
    "text": "monter de la terre et tomber du ciel en meme",
    "jalons": [
      102,
      146
    ]
  },
  "entite_252": {
    "label": "LOC",
    "text": "Alphonse",
    "jalons": [
      367,
      375
    ]
  },
  "entite_253": {
    "label": "MISC",
    "text": "venais de voler",
    "jalons": [
      1,
      16
    ]
  },
  "entite_254": {
    "label": "LOC",
    "text": "Marie-Aime",
    "jalons": [
      358,
      368
    ]
  },
  "entite_255": {
    "label": "LOC",
    "text": "Villevieille",
    "jalons": [
      119,
      131
    ]
  },
  "entite_256": {
    "label": "PER",
    "text": "Henri Deslois",
    "jalons": [
      276,
      289
    ]
  },
  "entite_257": {
    "label": "LOC",
    "text": "Aussitot",
    "jalons": [
      19,
      27
    ]
  },
  "entite_258": {
    "label": "PER",
    "text": "Il IlIi",
    "jalons": [
      3,
      10
    ]
  },
  "entite_259": {
    "label": "LOC",
    "text": "Bel-Il",
    "jalons": [
      468,
      474
    ]
  },
  "entite_260": {
    "label": "PER",
    "text": "Elle ferma la porte",
    "jalons": [
      4,
      23
    ]
  },
  "entite_261": {
    "label": "LOC",
    "text": "Bel",
    "jalons": [
      249,
      252
    ]
  },
  "entite_262": {
    "label": "ORG",
    "text": "Alors",
    "jalons": [
      506,
      511
    ]
  },
  "entite_263": {
    "label": "MISC",
    "text": "vous revenez  J'essayai de fixer mes",
    "jalons": [
      0,
      36
    ]
  },
  "entite_264": {
    "label": "MISC",
    "text": "Elle disait en se moquant",
    "jalons": [
      31,
      56
    ]
  },
  "entite_265": {
    "label": "LOC",
    "text": "Marie",
    "jalons": [
      443,
      448
    ]
  },
  "entite_266": {
    "label": "LOC",
    "text": "Elle tira",
    "jalons": [
      498,
      507
    ]
  },
  "entite_267": {
    "label": "MISC",
    "text": "L'idee me vint de me sauver",
    "jalons": [
      25,
      52
    ]
  },
  "entite_268": {
    "label": "LOC",
    "text": "Marie-Aime",
    "jalons": [
      229,
      239
    ]
  },
  "entite_269": {
    "label": "LOC",
    "text": "Marie-Claire",
    "jalons": [
      490,
      502
    ]
  },
  "entite_270": {
    "label": "MISC",
    "text": "ainsi dans la neigel Je relevai la tete",
    "jalons": [
      6,
      45
    ]
  },
  "entite_271": {
    "label": "PER",
    "text": "MARIE-CLAIRE Seule",
    "jalons": [
      322,
      340
    ]
  },
  "entite_272": {
    "label": "LOC",
    "text": "La grosse Mlanie",
    "jalons": [
      496,
      512
    ]
  },
  "entite_273": {
    "label": "MISC",
    "text": "Elle montra du doigt le rideau en baissant la voix",
    "jalons": [
      290,
      340
    ]
  },
  "entite_274": {
    "label": "PER",
    "text": "Desiree Joly",
    "jalons": [
      171,
      183
    ]
  },
  "entite_275": {
    "label": "PER",
    "text": "Desiree Joly",
    "jalons": [
      185,
      197
    ]
  },
  "entite_276": {
    "label": "LOC",
    "text": "Voyons",
    "jalons": [
      498,
      504
    ]
  },
  "entite_277": {
    "label": "LOC",
    "text": "ravail des",
    "jalons": [
      0,
      10
    ]
  },
  "entite_278": {
    "label": "PER",
    "text": "Elle n'avait",
    "jalons": [
      495,
      507
    ]
  },
  "entite_279": {
    "label": "PER",
    "text": "Jean le Rouge",
    "jalons": [
      489,
      502
    ]
  },
  "entite_280": {
    "label": "PER",
    "text": "Il s'ava",
    "jalons": [
      504,
      512
    ]
  },
  "entite_281": {
    "label": "PER",
    "text": "Henri Deslois",
    "jalons": [
      111,
      124
    ]
  },
  "entite_282": {
    "label": "LOC",
    "text": "Desiree-des-Ange",
    "jalons": [
      337,
      353
    ]
  },
  "entite_283": {
    "label": "LOC",
    "text": "Desiree-des-Ange",
    "jalons": [
      443,
      459
    ]
  },
  "entite_284": {
    "label": "LOC",
    "text": "Elle en connai",
    "jalons": [
      498,
      512
    ]
  },
  "entite_285": {
    "label": "LOC",
    "text": "Veronique",
    "jalons": [
      426,
      435
    ]
  },
  "entite_286": {
    "label": "LOC",
    "text": "La grosse",
    "jalons": [
      497,
      506
    ]
  },
  "entite_287": {
    "label": "MISC",
    "text": "Elle me prit la tete",
    "jalons": [
      486,
      506
    ]
  },
  "entite_288": {
    "label": "LOC",
    "text": "D'elle",
    "jalons": [
      486,
      492
    ]
  },
  "entite_289": {
    "label": "LOC",
    "text": "Toutes deux",
    "jalons": [
      494,
      505
    ]
  },
  "entite_290": {
    "label": "LOC",
    "text": "Marie-Aime",
    "jalons": [
      160,
      170
    ]
  },
  "entite_291": {
    "label": "LOC",
    "text": "Marie",
    "jalons": [
      226,
      231
    ]
  },
  "entite_292": {
    "label": "PER",
    "text": "Elle se leva du banc",
    "jalons": [
      34,
      54
    ]
  },
  "entite_293": {
    "label": "PER",
    "text": "Desiree Joly",
    "jalons": [
      184,
      196
    ]
  },
  "entite_294": {
    "label": "ORG",
    "text": "Toute",
    "jalons": [
      507,
      512
    ]
  },
  "entite_295": {
    "label": "PER",
    "text": "Marie",
    "jalons": [
      507,
      512
    ]
  },
  "entite_296": {
    "label": "PER",
    "text": "Melanie m'accompagna",
    "jalons": [
      7,
      27
    ]
  },
  "entite_297": {
    "label": "LOC",
    "text": "Les",
    "jalons": [
      501,
      504
    ]
  },
  "entite_298": {
    "label": "LOC",
    "text": "Paris",
    "jalons": [
      58,
      63
    ]
  },
  "entite_299": {
    "label": "LOC",
    "text": "Paris",
    "jalons": [
      105,
      110
    ]
  },
  "entite_300": {
    "label": "LOC",
    "text": "Paris",
    "jalons": [
      345,
      350
    ]
  },
  "entite_301": {
    "label": "LOC",
    "text": "Donnez",
    "jalons": [
      456,
      462
    ]
  },
  "entite_302": {
    "label": "PER",
    "text": "Henri Deslois",
    "jalons": [
      327,
      340
    ]
  }
}